pyvista/__init__.py
pyvista/_deprecate_positional_args.py
pyvista/_plot.py
pyvista/_version.py
pyvista/conftest.py
pyvista/errors.py
pyvista/py.typed
pyvista/report.py
pyvista/core/__init__.py
pyvista/core/_vtk_core.py
pyvista/core/cell.py
pyvista/core/celltype.py
pyvista/core/composite.py
pyvista/core/dataobject.py
pyvista/core/dataset.py
pyvista/core/datasetattributes.py
pyvista/core/errors.py
pyvista/core/grid.py
pyvista/core/objects.py
pyvista/core/partitioned.py
pyvista/core/pointset.py
pyvista/core/pyvista_ndarray.py
pyvista/core/wrappers.py
pyvista/core/_typing_core/__init__.py
pyvista/core/_typing_core/_aliases.py
pyvista/core/_typing_core/_array_like.py
pyvista/core/_typing_core/_dataset_types.py
pyvista/core/_validation/__init__.py
pyvista/core/_validation/_cast_array.py
pyvista/core/_validation/check.py
pyvista/core/_validation/validate.py
pyvista/core/filters/__init__.py
pyvista/core/filters/composite.py
pyvista/core/filters/data_object.py
pyvista/core/filters/data_set.py
pyvista/core/filters/image_data.py
pyvista/core/filters/poly_data.py
pyvista/core/filters/rectilinear_grid.py
pyvista/core/filters/structured_grid.py
pyvista/core/filters/unstructured_grid.py
pyvista/core/utilities/__init__.py
pyvista/core/utilities/arrays.py
pyvista/core/utilities/cell_quality.py
pyvista/core/utilities/cells.py
pyvista/core/utilities/docs.py
pyvista/core/utilities/features.py
pyvista/core/utilities/fileio.py
pyvista/core/utilities/geometric_objects.py
pyvista/core/utilities/geometric_sources.py
pyvista/core/utilities/helpers.py
pyvista/core/utilities/image_sources.py
pyvista/core/utilities/misc.py
pyvista/core/utilities/observers.py
pyvista/core/utilities/parametric_objects.py
pyvista/core/utilities/points.py
pyvista/core/utilities/reader.py
pyvista/core/utilities/state_manager.py
pyvista/core/utilities/transform.py
pyvista/core/utilities/transformations.py
pyvista/demos/__init__.py
pyvista/demos/demos.py
pyvista/demos/logo.py
pyvista/examples/2k_earth_daymap.jpg
pyvista-0.46.0.dist-info/licenses/AUTHORS.rst
pyvista-0.46.0.dist-info/licenses/LICENSE
pyvista-0.46.0.dist-info/METADATA
pyvista-0.46.0.dist-info/WHEEL
pyvista-0.46.0.dist-info/top_level.txt
pyvista-0.46.0.dist-info/RECORD
