Metadata-Version: 2.4
Name: pyvista
Version: 0.46.0
Summary: Easier Pythonic interface to VTK
Author-email: PyVista Developers <info@pyvista.org>
License-Expression: MIT
Project-URL: Bug Reports, https://github.com/pyvista/pyvista/issues
Project-URL: Documentation, https://docs.pyvista.org/
Project-URL: Homepage, https://github.com/pyvista/pyvista
Project-URL: Source Code, https://github.com/pyvista/pyvista
Keywords: mesh,numpy,plotting,vtk
Classifier: Development Status :: 5 - Production/Stable
Classifier: Intended Audience :: Science/Research
Classifier: Operating System :: MacOS
Classifier: Operating System :: Microsoft :: Windows
Classifier: Operating System :: POSIX
Classifier: Programming Language :: Python :: 3.10
Classifier: Programming Language :: Python :: 3.11
Classifier: Programming Language :: Python :: 3.12
Classifier: Programming Language :: Python :: 3.13
Classifier: Programming Language :: Python :: 3.9
Classifier: Topic :: Scientific/Engineering :: Information Analysis
Requires-Python: >=3.9
License-File: LICENSE
License-File: AUTHORS.rst
Requires-Dist: matplotlib>=3.0.1
Requires-Dist: numpy>=1.21.0
Requires-Dist: pillow
Requires-Dist: pooch
Requires-Dist: scooby>=0.5.1
Requires-Dist: typing-extensions
Requires-Dist: vtk!=9.4.0
Requires-Dist: vtk!=9.4.1
Requires-Dist: vtk<9.6.0
Provides-Extra: all
Requires-Dist: pyvista[colormaps,io,jupyter]; extra == "all"
Provides-Extra: colormaps
Requires-Dist: cmcrameri; extra == "colormaps"
Requires-Dist: cmocean; extra == "colormaps"
Requires-Dist: colorcet; extra == "colormaps"
Provides-Extra: io
Requires-Dist: imageio; extra == "io"
Requires-Dist: meshio>=5.2; extra == "io"
Provides-Extra: jupyter
Requires-Dist: ipywidgets; extra == "jupyter"
Requires-Dist: jupyter-server-proxy; extra == "jupyter"
Requires-Dist: nest_asyncio; extra == "jupyter"
Requires-Dist: trame-client>=2.12.7; extra == "jupyter"
Requires-Dist: trame-server>=2.11.7; extra == "jupyter"
Requires-Dist: trame-vtk>=2.5.8; extra == "jupyter"
Requires-Dist: trame-vuetify>=2.3.1; extra == "jupyter"
Requires-Dist: trame>=2.5.2; extra == "jupyter"
Dynamic: license-file
